README.md
setup.py
CIU_Py.egg-info/PKG-INFO
CIU_Py.egg-info/SOURCES.txt
CIU_Py.egg-info/dependency_links.txt
CIU_Py.egg-info/requires.txt
CIU_Py.egg-info/top_level.txt
ciu/__init__.py
ciu/ciu_core.py
ciu/ciu_object.py
ciu_tests/__init__.py
ciu_tests/ciu_tests.py