Metadata-Version: 2.1
Name: CIU-Py
Version: 1.0
Summary: Python documentation generator
Home-page: https://github.com/KaryFramling/py-ciu
Author: Vlad Apopei & Kary Främling
Author-email: ioan-vlad.apopei@aalto.fi, kary.framling@aalto.fi
License: MIT
Project-URL: Code, https://github.com/KaryFramling/py-ciu
Platform: any
Classifier: Development Status :: 5 - Production/Stable
Classifier: Operating System :: OS Independent
Classifier: Programming Language :: Python
Classifier: Intended Audience :: Developers
Classifier: License :: OSI Approved :: MIT License
Classifier: Topic :: Documentation
Requires-Python: >=3.6
